examples/__init__.py
examples/example_conductor.py
examples/example_server.py
vines_infer_sdk/__init__.py
vines_infer_sdk/conductor/__init__.py
vines_infer_sdk/logger/__init__.py
vines_infer_sdk/oss/__init__.py
vines_infer_sdk/server/__init__.py
vines_infer_sdk/utils/__init__.py
vines_infer_sdk/utils/files.py
vines_infer_sdk/utils/string.py
vines_infer_sdk-0.0.2.dist-info/METADATA
vines_infer_sdk-0.0.2.dist-info/WHEEL
vines_infer_sdk-0.0.2.dist-info/top_level.txt
vines_infer_sdk-0.0.2.dist-info/RECORD
