Metadata-Version: 2.1
Name: vines-infer-sdk
Version: 0.0.2
Summary: Vines Python 训练项目 SDK （供内部使用）
Home-page: https://github.com/inf-monkeys/viens-infer-helpers
Author: infmonkeys
Author-email: def@infmonkeys.com
License: MIT
Classifier: Development Status :: 3 - Alpha
Classifier: Intended Audience :: Developers
Classifier: License :: OSI Approved :: MIT License
Classifier: Programming Language :: Python :: 3
Classifier: Programming Language :: Python :: 3.6
Classifier: Programming Language :: Python :: 3.7
Classifier: Programming Language :: Python :: 3.8
Classifier: Programming Language :: Python :: 3.9
Classifier: Programming Language :: Python :: 3.10
Requires-Dist: boto3
Requires-Dist: botocore
Requires-Dist: flask
Requires-Dist: sentry-sdk
Requires-Dist: sentry-sdk[flask]
Requires-Dist: bullmq
